{
  "_class": "shapePath",
  "booleanOperation": -1,
  "do_objectID": "CF7BA9F1-8933-4523-9B8A-758259D81766",
  "edited": true,
  "exportOptions": {
    "_class": "exportOptions",
    "exportFormats": [
    ],
    "includedLayerIds": [
    ],
    "layerOptions": 0,
    "shouldTrim": false
  },
  "frame": {
    "_class": "rect",
    "constrainProportions": false,
    "height": 14,
    "width": 12,
    "x": 0,
    "y": 0
  },
  "isFlippedHorizontal": false,
  "isFlippedVertical": false,
  "isLocked": false,
  "isVisible": true,
  "layerListExpandedType": 0,
  "name": "Path",
  "nameIsFixed": false,
  "path": {
    "_class": "path",
    "isClosed": true,
    "pointRadiusBehaviour": 0,
    "points": [
      {
        "_class": "curvePoint",
        "cornerRadius": 0,
        "curveFrom": "{1, 0.96807142857142858}",
        "curveMode": 4,
        "curveTo": "{1, 0.92871428571428571}",
        "hasCurveFrom": true,
        "hasCurveTo": false,
        "point": "{1, 0.92871428571428571}"
      },
      {
        "_class": "curvePoint",
        "cornerRadius": 0,
        "curveFrom": "{0.91683333333333339, 1}",
        "curveMode": 4,
        "curveTo": "{0.96275000000000011, 1}",
        "hasCurveFrom": false,
        "hasCurveTo": true,
        "point": "{0.91683333333333339, 1}"
      },
      {
        "_class": "curvePoint",
        "cornerRadius": 0,
        "curveFrom": "{0.037333333333333336, 1}",
        "curveMode": 4,
        "curveTo": "{0.083416666666666653, 1}",
        "hasCurveFrom": true,
        "hasCurveTo": false,
        "point": "{0.083416666666666653, 1}"
      },
      {
        "_class": "curvePoint",
        "cornerRadius": 0,
        "curveFrom": "{0, 0.92849999999999999}",
        "curveMode": 4,
        "curveTo": "{0, 0.96799999999999997}",
        "hasCurveFrom": false,
        "hasCurveTo": true,
        "point": "{0, 0.92849999999999999}"
      },
      {
        "_class": "curvePoint",
        "cornerRadius": 0,
        "curveFrom": "{0, 0.66907142857142865}",
        "curveMode": 4,
        "curveTo": "{0, 0.8571428571428571}",
        "hasCurveFrom": true,
        "hasCurveTo": false,
        "point": "{0, 0.8571428571428571}"
      },
      {
        "_class": "curvePoint",
        "cornerRadius": 0,
        "curveFrom": "{0.34558333333333335, 0.59121428571428569}",
        "curveMode": 1,
        "curveTo": "{0.34558333333333335, 0.5912142857142858}",
        "hasCurveFrom": false,
        "hasCurveTo": false,
        "point": "{0.33333333333333331, 0.5714285714285714}"
      },
      {
        "_class": "curvePoint",
        "cornerRadius": 0,
        "curveFrom": "{0.26324999999999998, 0.45571428571428568}",
        "curveMode": 4,
        "curveTo": "{0.35241666666666666, 0.54221428571428576}",
        "hasCurveFrom": true,
        "hasCurveTo": true,
        "point": "{0.33333333333333331, 0.5}"
      },
      {
        "_class": "curvePoint",
        "cornerRadius": 0,
        "curveFrom": "{0.26441666666666669, 0.04192857142857144}",
        "curveMode": 4,
        "curveTo": "{0.25466666666666665, 0.38642857142857145}",
        "hasCurveFrom": true,
        "hasCurveTo": true,
        "point": "{0.25, 0.21428571428571427}"
      },
      {
        "_class": "curvePoint",
        "cornerRadius": 0,
        "curveFrom": "{0.5944166666666667, 0}",
        "curveMode": 2,
        "curveTo": "{0.40558333333333335, 0}",
        "hasCurveFrom": true,
        "hasCurveTo": true,
        "point": "{0.5, 0}"
      },
      {
        "_class": "curvePoint",
        "cornerRadius": 0,
        "curveFrom": "{0.7453333333333334, 0.38642857142857145}",
        "curveMode": 4,
        "curveTo": "{0.73558333333333337, 0.041857142857142857}",
        "hasCurveFrom": true,
        "hasCurveTo": true,
        "point": "{0.75, 0.21428571428571427}"
      },
      {
        "_class": "curvePoint",
        "cornerRadius": 0,
        "curveFrom": "{0.64758333333333329, 0.54214285714285715}",
        "curveMode": 4,
        "curveTo": "{0.7367499999999999, 0.45571428571428568}",
        "hasCurveFrom": true,
        "hasCurveTo": true,
        "point": "{0.66666666666666663, 0.5}"
      },
      {
        "_class": "curvePoint",
        "cornerRadius": 0,
        "curveFrom": "{0.65441666666666665, 0.59121428571428569}",
        "curveMode": 1,
        "curveTo": "{0.66666666666666663, 0.5714285714285714}",
        "hasCurveFrom": false,
        "hasCurveTo": false,
        "point": "{0.66666666666666663, 0.5714285714285714}"
      },
      {
        "_class": "curvePoint",
        "cornerRadius": 0,
        "curveFrom": "{1, 0.8571428571428571}",
        "curveMode": 4,
        "curveTo": "{1, 0.66907142857142865}",
        "hasCurveFrom": false,
        "hasCurveTo": true,
        "point": "{1, 0.8571428571428571}"
      }
    ]
  },
  "resizingConstraint": 63,
  "resizingType": 0,
  "rotation": 0,
  "shouldBreakMaskChain": false
}