{
  "_class": "group",
  "do_objectID": "19E8352E-8CB3-4FA8-A437-C22B86DAB278",
  "exportOptions": {
    "_class": "exportOptions",
    "exportFormats": [
    ],
    "includedLayerIds": [
    ],
    "layerOptions": 0,
    "shouldTrim": false
  },
  "frame": {
    "_class": "rect",
    "constrainProportions": false,
    "height": 40,
    "width": 44,
    "x": 108,
    "y": 0
  },
  "hasClickThrough": false,
  "isFlippedHorizontal": false,
  "isFlippedVertical": false,
  "isLocked": false,
  "isVisible": true,
  "layerListExpandedType": 0,
  "layers": [
    {
      "class": "shapeGroup",
      "id": "B4ADC149-6DC2-4832-9E05-8334D6D4DC23"
    },
    {
      "class": "text",
      "id": "21893B3D-35B0-4E4B-88CB-0E6A8238455D"
    }
  ],
  "name": "buttons/standard/affix/warning",
  "nameIsFixed": true,
  "resizingConstraint": 63,
  "resizingType": 0,
  "rotation": 0,
  "shouldBreakMaskChain": false,
  "style": {
    "_class": "style",
    "endDecorationType": 0,
    "miterLimit": 10,
    "startDecorationType": 0
  }
}