{
  "_class": "shapePath",
  "booleanOperation": -1,
  "do_objectID": "11E0991A-79D2-4595-8B50-C604765E4CC6",
  "edited": true,
  "exportOptions": {
    "_class": "exportOptions",
    "exportFormats": [
    ],
    "includedLayerIds": [
    ],
    "layerOptions": 0,
    "shouldTrim": false
  },
  "frame": {
    "_class": "rect",
    "constrainProportions": false,
    "height": 14.13,
    "width": 15,
    "x": 0,
    "y": 0
  },
  "isFlippedHorizontal": false,
  "isFlippedVertical": false,
  "isLocked": false,
  "isVisible": true,
  "layerListExpandedType": 0,
  "name": "Path",
  "nameIsFixed": false,
  "path": {
    "_class": "path",
    "isClosed": true,
    "pointRadiusBehaviour": 0,
    "points": [
      {
        "_class": "curvePoint",
        "cornerRadius": 0,
        "curveFrom": "{1, 0.73460721868365164}",
        "curveMode": 4,
        "curveTo": "{1, 0.53078556263269638}",
        "hasCurveFrom": true,
        "hasCurveTo": false,
        "point": "{1, 0.53078556263269638}"
      },
      {
        "_class": "curvePoint",
        "cornerRadius": 0,
        "curveFrom": "{0.73333333333333328, 0.99999999999999989}",
        "curveMode": 4,
        "curveTo": "{0.89133333333333342, 0.91153573956121714}",
        "hasCurveFrom": false,
        "hasCurveTo": true,
        "point": "{0.73333333333333328, 0.99999999999999989}"
      },
      {
        "_class": "curvePoint",
        "cornerRadius": 0,
        "curveFrom": "{0.85733333333333328, 0.84359518754423191}",
        "curveMode": 4,
        "curveTo": "{0.73333333333333328, 0.9256900212314223}",
        "hasCurveFrom": true,
        "hasCurveTo": false,
        "point": "{0.73333333333333328, 0.9256900212314223}"
      },
      {
        "_class": "curvePoint",
        "cornerRadius": 0,
        "curveFrom": "{0.93933333333333335, 0.27317763623496094}",
        "curveMode": 3,
        "curveTo": "{0.93933333333333335, 0.69780608634111796}",
        "hasCurveFrom": true,
        "hasCurveTo": true,
        "point": "{0.93933333333333335, 0.53078556263269627}"
      },
      {
        "_class": "curvePoint",
        "cornerRadius": 0,
        "curveFrom": "{0.2573333333333333, 0.064401981599433708}",
        "curveMode": 2,
        "curveTo": "{0.7426666666666667, 0.064401981599433708}",
        "hasCurveFrom": true,
        "hasCurveTo": true,
        "point": "{0.5, 0.064401981599433708}"
      },
      {
        "_class": "curvePoint",
        "cornerRadius": 0,
        "curveFrom": "{0.060666666666666667, 0.69780608634111807}",
        "curveMode": 3,
        "curveTo": "{0.060666666666666667, 0.27317763623496105}",
        "hasCurveFrom": true,
        "hasCurveTo": true,
        "point": "{0.060666666666666667, 0.53078556263269638}"
      },
      {
        "_class": "curvePoint",
        "cornerRadius": 0,
        "curveFrom": "{0.26666666666666666, 0.92569002123142241}",
        "curveMode": 4,
        "curveTo": "{0.14266666666666666, 0.84359518754423213}",
        "hasCurveFrom": false,
        "hasCurveTo": true,
        "point": "{0.26666666666666666, 0.92569002123142241}"
      },
      {
        "_class": "curvePoint",
        "cornerRadius": 0,
        "curveFrom": "{0.10866666666666666, 0.91153573956121725}",
        "curveMode": 4,
        "curveTo": "{0.26666666666666666, 1}",
        "hasCurveFrom": true,
        "hasCurveTo": false,
        "point": "{0.26666666666666666, 1}"
      },
      {
        "_class": "curvePoint",
        "cornerRadius": 0,
        "curveFrom": "{0, 0.23779193205944796}",
        "curveMode": 3,
        "curveTo": "{0, 0.73460721868365186}",
        "hasCurveFrom": true,
        "hasCurveTo": true,
        "point": "{0, 0.53078556263269638}"
      },
      {
        "_class": "curvePoint",
        "cornerRadius": 0,
        "curveFrom": "{0.77600000000000002, 0}",
        "curveMode": 2,
        "curveTo": "{0.224, 0}",
        "hasCurveFrom": true,
        "hasCurveTo": true,
        "point": "{0.5, 0}"
      },
      {
        "_class": "curvePoint",
        "cornerRadius": 0,
        "curveFrom": "{1, 0.53078556263269638}",
        "curveMode": 4,
        "curveTo": "{1, 0.23779193205944796}",
        "hasCurveFrom": false,
        "hasCurveTo": true,
        "point": "{1, 0.53078556263269638}"
      }
    ]
  },
  "resizingConstraint": 63,
  "resizingType": 0,
  "rotation": 0,
  "shouldBreakMaskChain": false
}