{
  "_class": "shapePath",
  "booleanOperation": -1,
  "do_objectID": "6FBEC957-99B7-4ED3-B54F-B77BD8016285",
  "edited": true,
  "exportOptions": {
    "_class": "exportOptions",
    "exportFormats": [
    ],
    "includedLayerIds": [
    ],
    "layerOptions": 0,
    "shouldTrim": false
  },
  "frame": {
    "_class": "rect",
    "constrainProportions": false,
    "height": 7.81,
    "width": 2.469999999999999,
    "x": 9.939999999999998,
    "y": 4.060069789314666
  },
  "isFlippedHorizontal": false,
  "isFlippedVertical": false,
  "isLocked": false,
  "isVisible": true,
  "layerListExpandedType": 0,
  "name": "Path",
  "nameIsFixed": false,
  "path": {
    "_class": "path",
    "isClosed": true,
    "pointRadiusBehaviour": 0,
    "points": [
      {
        "_class": "curvePoint",
        "cornerRadius": 0,
        "curveFrom": "{0.93117408906882659, 0}",
        "curveMode": 1,
        "curveTo": "{0.93117408906882659, 0}",
        "hasCurveFrom": false,
        "hasCurveTo": false,
        "point": "{0.93117408906882659, 0}"
      },
      {
        "_class": "curvePoint",
        "cornerRadius": 0,
        "curveFrom": "{0.032388663967611378, 0}",
        "curveMode": 4,
        "curveTo": "{0.068825910931174086, 0}",
        "hasCurveFrom": true,
        "hasCurveTo": false,
        "point": "{0.068825910931174086, 0}"
      },
      {
        "_class": "curvePoint",
        "cornerRadius": 0,
        "curveFrom": "{0, 0.025608194622279149}",
        "curveMode": 4,
        "curveTo": "{0, 0.011523687580025702}",
        "hasCurveFrom": false,
        "hasCurveTo": true,
        "point": "{0, 0.025608194622279149}"
      },
      {
        "_class": "curvePoint",
        "cornerRadius": 0,
        "curveFrom": "{0, 0.99103713188220222}",
        "curveMode": 4,
        "curveTo": "{0, 0.96542893725992318}",
        "hasCurveFrom": true,
        "hasCurveTo": false,
        "point": "{0, 0.96542893725992318}"
      },
      {
        "_class": "curvePoint",
        "cornerRadius": 0,
        "curveFrom": "{0.12145748987854213, 1}",
        "curveMode": 4,
        "curveTo": "{0.052631578947368043, 1}",
        "hasCurveFrom": false,
        "hasCurveTo": true,
        "point": "{0.12145748987854213, 1}"
      },
      {
        "_class": "curvePoint",
        "cornerRadius": 0,
        "curveFrom": "{0.97975708502024339, 1}",
        "curveMode": 4,
        "curveTo": "{0.89878542510121451, 1}",
        "hasCurveFrom": true,
        "hasCurveTo": false,
        "point": "{0.89878542510121451, 1}"
      },
      {
        "_class": "curvePoint",
        "cornerRadius": 0,
        "curveFrom": "{1, 0.96542893725992318}",
        "curveMode": 4,
        "curveTo": "{1, 0.98847631241997436}",
        "hasCurveFrom": false,
        "hasCurveTo": true,
        "point": "{1, 0.96542893725992318}"
      },
      {
        "_class": "curvePoint",
        "cornerRadius": 0,
        "curveFrom": "{1, 0.023047375160051294}",
        "curveMode": 1,
        "curveTo": "{1, 0.023047375160051294}",
        "hasCurveFrom": false,
        "hasCurveTo": false,
        "point": "{1, 0.023047375160051294}"
      },
      {
        "_class": "curvePoint",
        "cornerRadius": 0,
        "curveFrom": "{1, 0.010243277848911774}",
        "curveMode": 4,
        "curveTo": "{1, 0.02176696542893725}",
        "hasCurveFrom": true,
        "hasCurveTo": false,
        "point": "{1, 0.02176696542893725}"
      },
      {
        "_class": "curvePoint",
        "cornerRadius": 0,
        "curveFrom": "{0.93117408906882659, 0}",
        "curveMode": 4,
        "curveTo": "{0.96761133603238936, 0}",
        "hasCurveFrom": false,
        "hasCurveTo": true,
        "point": "{0.93117408906882659, 0}"
      }
    ]
  },
  "resizingConstraint": 63,
  "resizingType": 0,
  "rotation": 0,
  "shouldBreakMaskChain": false
}