{
  "_class": "shapePath",
  "booleanOperation": -1,
  "do_objectID": "86F1B25B-13D7-4728-9C4A-B5DDABFAE302",
  "edited": true,
  "exportOptions": {
    "_class": "exportOptions",
    "exportFormats": [
    ],
    "includedLayerIds": [
    ],
    "layerOptions": 0,
    "shouldTrim": false
  },
  "frame": {
    "_class": "rect",
    "constrainProportions": false,
    "height": 11.68,
    "width": 7.469999999999999,
    "x": 37.19,
    "y": 0.4100697893146608
  },
  "isFlippedHorizontal": false,
  "isFlippedVertical": false,
  "isLocked": false,
  "isVisible": true,
  "layerListExpandedType": 0,
  "name": "Path",
  "nameIsFixed": false,
  "path": {
    "_class": "path",
    "isClosed": true,
    "pointRadiusBehaviour": 0,
    "points": [
      {
        "_class": "curvePoint",
        "cornerRadius": 0,
        "curveFrom": "{1, 0.91609589041095885}",
        "curveMode": 4,
        "curveTo": "{1, 0.62243150684931514}",
        "hasCurveFrom": true,
        "hasCurveTo": false,
        "point": "{1, 0.62243150684931514}"
      },
      {
        "_class": "curvePoint",
        "cornerRadius": 0,
        "curveFrom": "{0.37215528781793861, 1}",
        "curveMode": 3,
        "curveTo": "{0.85140562248995988, 1}",
        "hasCurveFrom": true,
        "hasCurveTo": true,
        "point": "{0.59170013386880893, 1}"
      },
      {
        "_class": "curvePoint",
        "cornerRadius": 0,
        "curveFrom": "{0.2543507362784479, 0.92893835616438358}",
        "curveMode": 2,
        "curveTo": "{0.2543507362784479, 0.92893835616438358}",
        "hasCurveFrom": true,
        "hasCurveTo": true,
        "point": "{0.2543507362784479, 0.92893835616438358}"
      },
      {
        "_class": "curvePoint",
        "cornerRadius": 0,
        "curveFrom": "{0.23828647925033486, 0.97859589041095896}",
        "curveMode": 4,
        "curveTo": "{0.24899598393574293, 0.96832191780821908}",
        "hasCurveFrom": true,
        "hasCurveTo": true,
        "point": "{0.24230254350736313, 0.97345890410958902}"
      },
      {
        "_class": "curvePoint",
        "cornerRadius": 0,
        "curveFrom": "{0.22356091030789851, 0.9803082191780822}",
        "curveMode": 4,
        "curveTo": "{0.23159303882195506, 0.9803082191780822}",
        "hasCurveFrom": false,
        "hasCurveTo": true,
        "point": "{0.22356091030789851, 0.9803082191780822}"
      },
      {
        "_class": "curvePoint",
        "cornerRadius": 0,
        "curveFrom": "{0.012048192771084796, 0.9803082191780822}",
        "curveMode": 4,
        "curveTo": "{0.025435073627845362, 0.9803082191780822}",
        "hasCurveFrom": true,
        "hasCurveTo": false,
        "point": "{0.025435073627845362, 0.9803082191780822}"
      },
      {
        "_class": "curvePoint",
        "cornerRadius": 0,
        "curveFrom": "{0, 0.96575342465753422}",
        "curveMode": 4,
        "curveTo": "{0, 0.97345890410958902}",
        "hasCurveFrom": false,
        "hasCurveTo": true,
        "point": "{0, 0.96575342465753422}"
      },
      {
        "_class": "curvePoint",
        "cornerRadius": 0,
        "curveFrom": "{0.0026773761713524938, 0.0068493150684931555}",
        "curveMode": 4,
        "curveTo": "{0.0026773761713524938, 0.014554794520547937}",
        "hasCurveFrom": true,
        "hasCurveTo": false,
        "point": "{0.0026773761713524938, 0.014554794520547937}"
      },
      {
        "_class": "curvePoint",
        "cornerRadius": 0,
        "curveFrom": "{0.025435073627845362, 0}",
        "curveMode": 4,
        "curveTo": "{0.013386880856761518, 0}",
        "hasCurveFrom": false,
        "hasCurveTo": true,
        "point": "{0.025435073627845362, 0}"
      },
      {
        "_class": "curvePoint",
        "cornerRadius": 0,
        "curveFrom": "{0.3226238286479256, 0}",
        "curveMode": 4,
        "curveTo": "{0.31057563587684173, 0}",
        "hasCurveFrom": true,
        "hasCurveTo": false,
        "point": "{0.31057563587684173, 0}"
      },
      {
        "_class": "curvePoint",
        "cornerRadius": 0,
        "curveFrom": "{0.33333333333333459, 0.014554794520547937}",
        "curveMode": 4,
        "curveTo": "{0.33333333333333459, 0.0068493150684931555}",
        "hasCurveFrom": false,
        "hasCurveTo": true,
        "point": "{0.33333333333333459, 0.014554794520547937}"
      },
      {
        "_class": "curvePoint",
        "cornerRadius": 0,
        "curveFrom": "{0.33333333333333459, 0.33732876712328774}",
        "curveMode": 4,
        "curveTo": "{0.33333333333333459, 0.33732876712328774}",
        "hasCurveFrom": true,
        "hasCurveTo": false,
        "point": "{0.33333333333333459, 0.33732876712328774}"
      },
      {
        "_class": "curvePoint",
        "cornerRadius": 0,
        "curveFrom": "{0.60374832663989364, 0.29195205479452069}",
        "curveMode": 4,
        "curveTo": "{0.44310575635876875, 0.29195205479452069}",
        "hasCurveFrom": false,
        "hasCurveTo": true,
        "point": "{0.60374832663989364, 0.29195205479452069}"
      },
      {
        "_class": "curvePoint",
        "cornerRadius": 0,
        "curveFrom": "{0.76305220883534186, 0.29023972602739728}",
        "curveMode": 4,
        "curveTo": "{0.60240963855421692, 0.29023972602739728}",
        "hasCurveFrom": true,
        "hasCurveTo": false,
        "point": "{0.60240963855421692, 0.29023972602739728}"
      },
      {
        "_class": "curvePoint",
        "cornerRadius": 0,
        "curveFrom": "{1, 0.62243150684931514}",
        "curveMode": 4,
        "curveTo": "{1, 0.32876712328767127}",
        "hasCurveFrom": false,
        "hasCurveTo": true,
        "point": "{1, 0.62243150684931514}"
      }
    ]
  },
  "resizingConstraint": 63,
  "resizingType": 0,
  "rotation": 0,
  "shouldBreakMaskChain": false
}