{
  "_class": "shapeGroup",
  "clippingMaskMode": 0,
  "do_objectID": "44E9A55F-6BD6-440C-AF43-365AACBE59C8",
  "exportOptions": {
    "_class": "exportOptions",
    "exportFormats": [
    ],
    "includedLayerIds": [
    ],
    "layerOptions": 0,
    "shouldTrim": false
  },
  "frame": {
    "_class": "rect",
    "constrainProportions": true,
    "height": 47.98437748745557,
    "width": 47.98437748745558,
    "x": 0.007811256271452294,
    "y": 0.00781125627221968
  },
  "hasClickThrough": false,
  "hasClippingMask": false,
  "isFlippedHorizontal": false,
  "isFlippedVertical": false,
  "isLocked": false,
  "isVisible": true,
  "layerListExpandedType": 0,
  "layers": [
    {
      "class": "rectangle",
      "id": "5E6721A7-AFCA-43FA-9C0A-FC31B36AE76A"
    },
    {
      "class": "rectangle",
      "id": "BFAB5D55-C6AB-4E1F-A5F5-E4780ACA0A45"
    }
  ],
  "name": "close-icon",
  "nameIsFixed": true,
  "resizingConstraint": 45,
  "resizingType": 3,
  "rotation": 0,
  "shouldBreakMaskChain": false,
  "style": {
    "sharedObjectID": "C9B43A7F-4E67-4A0D-AFC9-A53389280A5A"
  },
  "windingRule": 1
}